{"104568":{"detail":{"date":"2000-03-23","platform":"TV","images":{"small":"https://lain.bgm.tv/r/200/pic/cover/l/70/a8/104568_OZmF6.jpg","grid":"https://lain.bgm.tv/r/100/pic/cover/l/70/a8/104568_OZmF6.jpg","large":"https://lain.bgm.tv/pic/cover/l/70/a8/104568_OZmF6.jpg","medium":"https://lain.bgm.tv/r/800/pic/cover/l/70/a8/104568_OZmF6.jpg","common":"https://lain.bgm.tv/r/400/pic/cover/l/70/a8/104568_OZmF6.jpg"},"summary":"　３月23日、テレビ朝日でオンエアされるＳＭＡＰの特別番組「スマアニメＳＰ（仮）」内で、小池健の最新短編アニメが放映される。これは同局の「Ｓｍａ　ＳＴＡＴＩＯＮ!!」番組内で放映された短編アニメシリーズ「スマアニメ」の新作で、１分半程度の作品×３本という内容。尺は短いながら、過激なノリと高密度作画が炸裂する相当イカシた仕上がりだ。実際に制作されたのは『ＡＮＩＭＡＴＲＩＸ』「ＷＯＲＬＤ　ＲＥＣＯＲＤ」と同時期で、完成後も永らく未放映のままだったが、今回ようやく初のお披露目となった。ファンは見逃し厳禁。放映日時は３月23日（火）深夜０時９分～39分（時間は変更することがあります）。その他、秋元きつねの「ムダオヤジ」と、太田洋康＆富岡聡の「ＭＥＮ’Ｓ　Ｍｉｋａｎ　Ｉｎ　ｔｈｅ　Ｒｏｏｍ」という２本のＣＧアニメも同番組内で放映される。\r\n　また、ファンならすでにご存じだろうが、ＤＲＥＡＭＳ　ＣＯＭＥ　ＴＲＵＥのシングル「やさしいキスをして」のジャケットイラストも小池健が手掛けている。まだ御覧になっていない方は要チェキ！","name":"Sma STATION!! スマアニメSP","name_cn":"SMAnime","tags":[{"name":"独立ova","count":3,"total_cont":0},{"name":"TV","count":1,"total_cont":0},{"name":"空","count":1,"total_cont":0},{"name":"原创","count":1,"total_cont":0},{"name":"OVA","count":1,"total_cont":0}],"infobox":[{"key":"中文名","value":"SMAnime"},{"key":"话数","value":"3"},{"key":"放送开始","value":"2000年3月23日"},{"key":"播放电视台","value":"テレビ朝日"}],"rating":{"rank":0,"total":2,"count":{"1":0,"2":0,"3":0,"4":0,"5":2,"6":0,"7":0,"8":0,"9":0,"10":0},"score":5},"total_episodes":3,"collection":{"on_hold":1,"dropped":7,"wish":6,"collect":4,"doing":0},"id":104568,"eps":3,"meta_tags":["TV"],"volumes":0,"series":false,"locked":false,"nsfw":false,"type":2},"episodes":[{"airdate":"","name":"","name_cn":"","duration":"","desc":"","ep":1,"sort":1,"id":401555,"subject_id":104568,"comment":0,"type":0,"disc":0,"duration_seconds":0},{"airdate":"","name":"","name_cn":"","duration":"","desc":"","ep":2,"sort":2,"id":401556,"subject_id":104568,"comment":0,"type":0,"disc":0,"duration_seconds":0},{"airdate":"","name":"","name_cn":"","duration":"","desc":"","ep":3,"sort":3,"id":401557,"subject_id":104568,"comment":0,"type":0,"disc":0,"duration_seconds":0}],"updatedAt":"2026-05-01T14:38:46.985Z"}}